aibs_informatics_core/__init__.py
aibs_informatics_core/_version.py
aibs_informatics_core/collections.py
aibs_informatics_core/env.py
aibs_informatics_core/exceptions.py
aibs_informatics_core/py.typed
aibs_informatics_core/executors/__init__.py
aibs_informatics_core/executors/base.py
aibs_informatics_core/executors/cli.py
aibs_informatics_core/models/__init__.py
aibs_informatics_core/models/data_sync.py
aibs_informatics_core/models/email_address.py
aibs_informatics_core/models/status.py
aibs_informatics_core/models/unique_ids.py
aibs_informatics_core/models/version.py
aibs_informatics_core/models/api/__init__.py
aibs_informatics_core/models/api/http_parameters.py
aibs_informatics_core/models/api/route.py
aibs_informatics_core/models/aws/__init__.py
aibs_informatics_core/models/aws/batch.py
aibs_informatics_core/models/aws/core.py
aibs_informatics_core/models/aws/dynamodb.py
aibs_informatics_core/models/aws/efs.py
aibs_informatics_core/models/aws/iam.py
aibs_informatics_core/models/aws/lambda_.py
aibs_informatics_core/models/aws/s3.py
aibs_informatics_core/models/aws/sfn.py
aibs_informatics_core/models/aws/sns.py
aibs_informatics_core/models/base/__init__.py
aibs_informatics_core/models/base/_pydantic_fields.py
aibs_informatics_core/models/base/_pydantic_model.py
aibs_informatics_core/models/base/custom_fields.py
aibs_informatics_core/models/base/field_utils.py
aibs_informatics_core/models/base/model.py
aibs_informatics_core/models/db/__init__.py
aibs_informatics_core/models/db/base.py
aibs_informatics_core/models/db/type_defs.py
aibs_informatics_core/models/demand_execution/__init__.py
aibs_informatics_core/models/demand_execution/job_param.py
aibs_informatics_core/models/demand_execution/job_param_resolver.py
aibs_informatics_core/models/demand_execution/metadata.py
aibs_informatics_core/models/demand_execution/model.py
aibs_informatics_core/models/demand_execution/param_pair.py
aibs_informatics_core/models/demand_execution/parameters.py
aibs_informatics_core-0.3.0.dist-info/licenses/LICENSE
aibs_informatics_core-0.3.0.dist-info/METADATA
aibs_informatics_core-0.3.0.dist-info/WHEEL
aibs_informatics_core-0.3.0.dist-info/entry_points.txt
aibs_informatics_core-0.3.0.dist-info/top_level.txt
aibs_informatics_core-0.3.0.dist-info/RECORD
