Metadata-Version: 2.4
Name: aibs-informatics-core
Version: 0.3.0
Summary: Core package for informatics projects at the Allen Institute for Brain Science
Author: AIBS Informatics Group
Maintainer: AIBS Informatics Group
License: Allen Institute Software License – This software license is the 2-clause BSD 
Project-URL: Documentation, https://.github.io/aibs-informatics-core/
Project-URL: Homepage, https://github.com/AllenInstitute/aibs-informatics-core/
Project-URL: Issues, https://github.com/AllenInstitute/aibs-informatics-core/issues
Project-URL: Repository, https://github.com/AllenInstitute/aibs-informatics-core/
Requires-Python: >=3.9
License-File: LICENSE
Requires-Dist: marshmallow~=3.22.0
Requires-Dist: dataclasses-json~=0.6.7
Requires-Dist: pathlib-abc
Requires-Dist: python-dateutil
Requires-Dist: pytz
Requires-Dist: pyyaml~=6.0
Requires-Dist: requests
Requires-Dist: typing_inspect
Requires-Dist: typing-extensions~=4.0; python_version < "3.11"
Provides-Extra: pydantic
Requires-Dist: pydantic<3,>=2.0.3; extra == "pydantic"
Provides-Extra: dev
Requires-Dist: aibs-informatics-core[pydantic]; extra == "dev"
Requires-Dist: aibs-informatics-test-resources~=0.1; extra == "dev"
Requires-Dist: mypy~=1.15.0; extra == "dev"
Dynamic: license-file
